README.md
setup.py
lokoguard_crashlytic/__init__.py
lokoguard_crashlytic/lokoguard_crashlytic.py
lokoguard_crashlytic.egg-info/PKG-INFO
lokoguard_crashlytic.egg-info/SOURCES.txt
lokoguard_crashlytic.egg-info/dependency_links.txt
lokoguard_crashlytic.egg-info/requires.txt
lokoguard_crashlytic.egg-info/top_level.txt